{
  "name": "techcommunity-banner-customization",
  "component": true,
  "license_url": null,
  "about_url": null,
  "authors": null,
  "theme_version": null,
  "minimum_discourse_version": null,
  "maximum_discourse_version": null,
  "assets": {
    "home-page-background-image": "assets/home-page-background-image.jpg",
    "small-arrow_blue": "assets/small-arrow_blue.png",
    "small-arrow_white": "assets/small-arrow_white.png"
  },
  "color_schemes": {
  },
  "modifiers": {
  },
  "learn_more": "https://meta.discourse.org/t/beginners-guide-to-using-discourse-themes/91966"
}